setup.py
client_chat_app.egg-info/PKG-INFO
client_chat_app.egg-info/SOURCES.txt
client_chat_app.egg-info/dependency_links.txt
client_chat_app.egg-info/requires.txt
client_chat_app.egg-info/top_level.txt
server/__init__.py
server/server.py
server/commons/__init__.py
server/commons/decorators.py
server/commons/descriptors.py
server/commons/errors.py
server/commons/metaclasses.py
server/commons/utils.py
server/commons/variables.py
server/logs/__init__.py
server/logs/config_client_logs.py
server/logs/config_server_logs.py
server/server/__init__.py
server/server/add_user.py
server/server/config_window.py
server/server/core.py
server/server/database.py
server/server/main_window.py
server/server/remove_user.py
server/server/stat_window.py