Metadata-Version: 2.1
Name: client-chat-app
Version: 0.0.1
Summary: client
Author: dmitrycider
Author-email: dimkasidorow@gmail.com
